setup.cfg
setup.py
bin/fixnulls.py
scorpion/__init__.py
scorpion/arch.py
scorpion/parallel.py
scorpion/settings.py
scorpion/sharedobj.py
scorpion.egg-info/PKG-INFO
scorpion.egg-info/SOURCES.txt
scorpion.egg-info/dependency_links.txt
scorpion.egg-info/requires.txt
scorpion.egg-info/top_level.txt
scorpion/bottomup/__init__.py
scorpion/bottomup/bounding_box.py
scorpion/bottomup/cluster.py
scorpion/learners/__init__.py
scorpion/learners/cn2sd/__init__.py
scorpion/learners/cn2sd/refiner.py
scorpion/learners/cn2sd/rule.py
scorpion/misc/__init__.py
scorpion/misc/genbaddata.py
scorpion/misc/genfecdata.py
scorpion/misc/genmultidimdata.py
scorpion/misc/gensinglecluster.py
scorpion/misc/plot.py
scorpion/misc/save_marcua_data.py
scorpion/sigmod/__init__.py
scorpion/sigmod/adjgraph.py
scorpion/sigmod/basic.py
scorpion/sigmod/bdt.py
scorpion/sigmod/bdtpartitioner.py
scorpion/sigmod/bdtq.py
scorpion/sigmod/bdtsingle.py
scorpion/sigmod/clique.py
scorpion/sigmod/frontier.py
scorpion/sigmod/grouper.py
scorpion/sigmod/merger.py
scorpion/sigmod/naive.py
scorpion/sigmod/naiveclique.py
scorpion/sigmod/naivegrouper.py
scorpion/sigmod/ndt.py
scorpion/sigmod/newbdtp.py
scorpion/sigmod/node.py
scorpion/sigmod/overlap.py
scorpion/sigmod/rangemerger.py
scorpion/sigmod/sampler.py
scorpion/sigmod/streamrangemerger.py
scorpion/sigmod/svm.py
scorpion/tests/__init__.py
scorpion/tests/common.py
scorpion/tests/gentestdata.py
scorpion/tests/plot_naive_bests.py
scorpion/tests/recompute_accuracy.py
scorpion/tests/run_cache_experiments.py
scorpion/tests/run_realworld_experiments.py
scorpion/tests/run_synth_experiments.py
scorpion/tests/setup_experiments.py
scorpion/tests/test.py
scorpion/tests/testsynth.py
scorpion/tests/testtopdown.py
scorpion/util/__init__.py
scorpion/util/misc.py
scorpion/util/prob.py
scorpion/util/rangeutil.py
scorpion/util/render.py
scorpion/util/status.py
scorpion/util/table.py
tests/unit/adjgraph.py
tests/unit/render.py
tests/unit/sharedobj.py