Metadata-Version: 1.0
Name: scorpion
Version: 0.0.6
Summary: scorpion
Home-page: http://github.com/sirrice/scorpion
Author: Eugene Wu
Author-email: eugenewu@mit.edu
License: MIT
Platform: UNKNOWN
